{
    "QQQ": {
        "assetMainType": "EQUITY",
        "assetSubType": "ETF",
        "quoteType": "NBBO",
        "realtime": true,
        "ssid": 48644470,
        "symbol": "QQQ",
        "extended": {
            "askPrice": 0.0,
            "askSize": 0,
            "bidPrice": 0.0,
            "bidSize": 0,
            "lastPrice": 518.93,
            "lastSize": 4,
            "mark": 0.0,
            "quoteTime": 1748592000000,
            "totalVolume": 0,
            "tradeTime": 1748591983000
        },
        "fundamental": {
            "avg10DaysVolume": 51974768.0,
            "avg1YearVolume": 37737123.0,
            "declarationDate": "2025-03-21T00:00:00Z",
            "divAmount": 2.86284,
            "divExDate": "2025-03-24T00:00:00Z",
            "divFreq": 4,
            "divPayAmount": 0.71571,
            "divPayDate": "2025-04-30T00:00:00Z",
            "divYield": 0.5517,
            "eps": 126.30331,
            "fundLeverageFactor": 0.0,
            "lastEarningsDate": "2024-12-27T00:00:00Z",
            "nextDivExDate": "2025-06-24T00:00:00Z",
            "nextDivPayDate": "2025-07-30T00:00:00Z",
            "peRatio": 4.11652
        },
        "quote": {
            "52WeekHigh": 540.81,
            "52WeekLow": 402.39,
            "askMICId": "ARCX",
            "askPrice": 515.04,
            "askSize": 3,
            "askTime": 1748628305239,
            "bidMICId": "ARCX",
            "bidPrice": 515.03,
            "bidSize": 2,
            "bidTime": 1748628305167,
            "closePrice": 519.93,
            "highPrice": 519.86,
            "lastMICId": "XADF",
            "lastPrice": 515.03,
            "lastSize": 100,
            "lowPrice": 511.93,
            "mark": 515.03,
            "markChange": -4.9,
            "markPercentChange": -0.94243456,
            "netChange": -4.9,
            "netPercentChange": -0.94243456,
            "openPrice": 519.44,
            "postMarketChange": 0.0,
            "postMarketPercentChange": 0.0,
            "quoteTime": 1748628305239,
            "securityStatus": "Normal",
            "totalVolume": 44370749,
            "tradeTime": 1748628305166
        },
        "reference": {
            "cusip": "46090E103",
            "description": "INVESCO QQQ TRUST",
            "exchange": "Q",
            "exchangeName": "NASDAQ",
            "isHardToBorrow": false,
            "isShortable": true,
            "htbQuantity": 1477997,
            "htbRate": 0.0
        },
        "regular": {
            "regularMarketLastPrice": 515.03,
            "regularMarketLastSize": 100,
            "regularMarketNetChange": -4.9,
            "regularMarketPercentChange": -0.94243456,
            "regularMarketTradeTime": 1748628305166
        }
    },
    "NVDA": {
        "assetMainType": "EQUITY",
        "assetSubType": "COE",
        "quoteType": "NBBO",
        "realtime": true,
        "ssid": 382397811,
        "symbol": "NVDA",
        "extended": {
            "askPrice": 0.0,
            "askSize": 0,
            "bidPrice": 0.0,
            "bidSize": 0,
            "lastPrice": 137.9,
            "lastSize": 28,
            "mark": 0.0,
            "quoteTime": 1748592000000,
            "totalVolume": 0,
            "tradeTime": 1748591993000
        },
        "fundamental": {
            "avg10DaysVolume": 224277344.0,
            "avg1YearVolume": 286659478.0,
            "declarationDate": "2025-02-26T00:00:00Z",
            "divAmount": 0.04,
            "divExDate": "2025-03-12T00:00:00Z",
            "divFreq": 4,
            "divPayAmount": 0.01,
            "divPayDate": "2025-04-02T00:00:00Z",
            "divYield": 0.02967,
            "eps": 2.94,
            "fundLeverageFactor": 0.0,
            "lastEarningsDate": "2025-05-28T00:00:00Z",
            "nextDivExDate": "2025-06-12T00:00:00Z",
            "nextDivPayDate": "2025-07-02T00:00:00Z",
            "peRatio": 47.0868
        },
        "quote": {
            "52WeekHigh": 153.13,
            "52WeekLow": 86.62,
            "askMICId": "EDGX",
            "askPrice": 133.95,
            "askSize": 7,
            "askTime": 1748628305156,
            "bidMICId": "XNAS",
            "bidPrice": 133.94,
            "bidSize": 3,
            "bidTime": 1748628305495,
            "closePrice": 139.19,
            "highPrice": 139.62,
            "lastMICId": "BATS",
            "lastPrice": 133.945,
            "lastSize": 300,
            "lowPrice": 132.92,
            "mark": 133.945,
            "markChange": -5.245,
            "markPercentChange": -3.76823048,
            "netChange": -5.245,
            "netPercentChange": -3.76823048,
            "openPrice": 138.715,
            "postMarketChange": 0.0,
            "postMarketPercentChange": 0.0,
            "quoteTime": 1748628305495,
            "securityStatus": "Normal",
            "totalVolume": 200156168,
            "tradeTime": 1748628305325
        },
        "reference": {
            "cusip": "67066G104",
            "description": "NVIDIA CORP",
            "exchange": "Q",
            "exchangeName": "NASDAQ",
            "isHardToBorrow": false,
            "isShortable": true,
            "htbQuantity": 71632094,
            "htbRate": 0.0
        },
        "regular": {
            "regularMarketLastPrice": 133.945,
            "regularMarketLastSize": 300,
            "regularMarketNetChange": -5.245,
            "regularMarketPercentChange": -3.76823048,
            "regularMarketTradeTime": 1748628305325
        }
    },
    "GME": {
        "assetMainType": "EQUITY",
        "assetSubType": "COE",
        "quoteType": "NBBO",
        "realtime": true,
        "ssid": 1465944785,
        "symbol": "GME",
        "extended": {
            "askPrice": 0.0,
            "askSize": 0,
            "bidPrice": 0.0,
            "bidSize": 0,
            "lastPrice": 29.0,
            "lastSize": 41,
            "mark": 0.0,
            "quoteTime": 1748592000000,
            "totalVolume": 0,
            "tradeTime": 1748591941000
        },
        "fundamental": {
            "avg10DaysVolume": 17864856.0,
            "avg1YearVolume": 16581662.0,
            "declarationDate": "2019-03-04T00:00:00Z",
            "divAmount": 1.52,
            "divExDate": "2019-03-14T00:00:00Z",
            "divFreq": 4,
            "divPayAmount": 0.38,
            "divPayDate": "2019-03-29T00:00:00Z",
            "divYield": 5.14034,
            "eps": 0.33,
            "fundLeverageFactor": 0.0,
            "lastEarningsDate": "2025-03-25T00:00:00Z",
            "nextDivExDate": "2019-06-14T00:00:00Z",
            "nextDivPayDate": "2019-07-01T00:00:00Z",
            "peRatio": 89.60606
        },
        "quote": {
            "52WeekHigh": 48.0,
            "52WeekLow": 18.73,
            "askMICId": "BATS",
            "askPrice": 29.79,
            "askSize": 3,
            "askTime": 1748628298032,
            "bidMICId": "XNYS",
            "bidPrice": 29.76,
            "bidSize": 2,
            "bidTime": 1748628300038,
            "closePrice": 29.57,
            "highPrice": 30.49,
            "lastMICId": "XADF",
            "lastPrice": 29.76,
            "lastSize": 168,
            "lowPrice": 29.185,
            "mark": 29.76,
            "markChange": 0.19,
            "markPercentChange": 0.64254312,
            "netChange": 0.19,
            "netPercentChange": 0.64254312,
            "openPrice": 29.2,
            "postMarketChange": 0.0,
            "postMarketPercentChange": 0.0,
            "quoteTime": 1748628300038,
            "securityStatus": "Normal",
            "totalVolume": 7211554,
            "tradeTime": 1748628298396
        },
        "reference": {
            "cusip": "36467W109",
            "description": "GAMESTOP CORP NEW A",
            "exchange": "N",
            "exchangeName": "NYSE",
            "isHardToBorrow": false,
            "isShortable": true,
            "htbQuantity": 0,
            "htbRate": 0.0
        },
        "regular": {
            "regularMarketLastPrice": 29.76,
            "regularMarketLastSize": 168,
            "regularMarketNetChange": 0.19,
            "regularMarketPercentChange": 0.64254312,
            "regularMarketTradeTime": 1748628298396
        }
    }
}